<package>
  <description brief="people_detector">
     people_detector
  </description>
  <author>Oscar Martinez Mozos, Dejan Pangercic(ROS)</author>
  <license>BSD</license>
  <review status="unreviewed" notes=""/>
  <url>http://ros.org/wiki/people_detector</url>
  <depend package="roscpp" />
  <depend package="std_msgs" />
  <depend package="sensor_msgs" />
  
  <export>
    <cpp cflags="-I${prefix}/people_detector/common" lflags="-Wl,-rpath,${prefix}/people_detector/common -L${prefix}/people_detector/common -lcommon" />
    <cpp cflags="-I${prefix}/people_detector/features" lflags="-Wl,-rpath,${prefix}/people_detector/features -L${prefix}/people_detector/features -lfeatures" />
    <cpp cflags="-I${prefix}/people_detector/linalg" lflags="-Wl,-rpath,${prefix}/people_detector/linalg -L${prefix}/people_detector/linalg -llinalg" />
    <cpp cflags="-I${prefix}/people_detector/PeopleDetector" lflags="-Wl,-rpath,${prefix}/people_detector/PeopleDetector -L${prefix}/people_detector/PeopleDetector -lPeopleDetector" />
  </export>
</package>


